vhdl/dev/mux/mux.vhd
library ieee;
use ieee.std_logic_1164.all;
use ieee.numeric_std.all;

-- expose signals outside of this module
entity mux is
port(
    -- inputs
    sig_a   : in unsigned(7 downto 0);
    sig_b   : in unsigned(7 downto 0);
    sig_c   : in unsigned(7 downto 0);
    sig_d   : in unsigned(7 downto 0);
    sig_sel : in unsigned(1 downto 0);

    -- outputs
    sig_out : out unsigned(7 downto 0));
end entity;

architecture mux_arq of mux is
begin

    process(sig_sel, sig_a, sig_b, sig_c, sig_d) is 
    begin

        case sig_sel is
            when "00" =>
                sig_out <= sig_a;
            when "01" =>
                sig_out <= sig_b;
            when "10" =>
                sig_out <= sig_c;
            when "11" =>
                sig_out <= sig_d;
            when others =>
                sig_out <= (others => 'X');
        end case;

    end process;

end architecture;

vhdl/dev/mux/mux_tb.vhd
library ieee;
use ieee.std_logic_1164.all;
use ieee.numeric_std.all;

entity mux_tb is
end entity;

architecture mux_arq of mux_tb is

    signal sig_a : unsigned(7 downto 0) := x"AA";
    signal sig_b : unsigned(7 downto 0) := x"BB";
    signal sig_c : unsigned(7 downto 0) := x"CC";
    signal sig_d : unsigned(7 downto 0) := x"DD";

    signal sig_sel : unsigned(1 downto 0) := (others => '1');
    signal sig_out : unsigned(7 downto 0);

begin

    -- instance of `mux` module
    mux_a : entity work.mux(mux_arq) port map(
        sig_sel => sig_sel,
        sig_a   => sig_a,
        sig_b   => sig_b,
        sig_c   => sig_c,
        sig_d   => sig_d,
        sig_out => sig_out);

    process is 
    begin
        sig_sel <= sig_sel + 1;
        wait for 100 us;
    end process;

end architecture;

vhdl/dev/mux/mux_tb.vcd
$date
  Thu Apr 16 11:22:17 2026
$end
$version
  GHDL v0
$end
$timescale
  1 fs
$end
$scope module standard $end
$upscope $end
$scope module std_logic_1164 $end
$upscope $end
$scope module numeric_std $end
$upscope $end
$scope module mux_tb $end
$var reg 8 ! sig_a[7:0] $end
$var reg 8 " sig_b[7:0] $end
$var reg 8 # sig_c[7:0] $end
$var reg 8 $ sig_d[7:0] $end
$var reg 2 % sig_sel[1:0] $end
$var reg 8 & sig_out[7:0] $end
$scope module mux_a $end
$var reg 8 ' sig_a[7:0] $end
$var reg 8 ( sig_b[7:0] $end
$var reg 8 ) sig_c[7:0] $end
$var reg 8 * sig_d[7:0] $end
$var reg 2 + sig_sel[1:0] $end
$var reg 8 , sig_out[7:0] $end
$upscope $end
$upscope $end
$enddefinitions $end
#0
b10101010 !
b10111011 "
b11001100 #
b11011101 $
b00 %
b10101010 &
b10101010 '
b10111011 (
b11001100 )
b11011101 *
b00 +
b10101010 ,
#100000000000
b01 %
b10111011 &
b01 +
b10111011 ,
#200000000000
b10 %
b11001100 &
b10 +
b11001100 ,
#300000000000
b11 %
b11011101 &
b11 +
b11011101 ,
#400000000000
b00 %
b10101010 &
b00 +
b10101010 ,
#500000000000
b01 %
b10111011 &
b01 +
b10111011 ,
#600000000000
b10 %
b11001100 &
b10 +
b11001100 ,
#700000000000
b11 %
b11011101 &
b11 +
b11011101 ,
#800000000000
b00 %
b10101010 &
b00 +
b10101010 ,
#900000000000
b01 %
b10111011 &
b01 +
b10111011 ,
#1000000000000
b10 %
b11001100 &
b10 +
b11001100 ,
